ientc_cognito_jwt/__init__.py
ientc_cognito_jwt/cognito_jwt_utils.py
ientc_cognito_jwt-0.9.dist-info/METADATA
ientc_cognito_jwt-0.9.dist-info/WHEEL
ientc_cognito_jwt-0.9.dist-info/top_level.txt
ientc_cognito_jwt-0.9.dist-info/RECORD
