Metadata-Version: 2.4
Name: ientc_cognito_jwt
Version: 0.9
Summary: A JWT utilities package for IENTC
Home-page: https://ientc.com
Author: Jesús Cota
Author-email: cota@ientc.com
Requires-Dist: httpx
Requires-Dist: python-jose
Dynamic: author
Dynamic: author-email
Dynamic: description
Dynamic: description-content-type
Dynamic: home-page
Dynamic: requires-dist
Dynamic: summary
